<map>
  <entry>
    <string>Name</string>
    <string>MoreDamagingProjectile</string>
  </entry>
  <entry>
    <string>PartType</string>
    <string>Projectile</string>
  </entry>
  <entry>
    <string>Tags</string>
    <string>Basic</string>
  </entry>
  <entry>
    <string>BoundingWidth</string>
    <double>10.0</double>
  </entry>
  <entry>
    <string>BoundingHeight</string>
    <double>10.0</double>
  </entry>
  <entry>
    <string>Image</string>
    <string>images/bluefire.png</string>
  </entry>
  <entry>
    <string>Group</string>
    <string>Default</string>
  </entry>
  <entry>
    <string>Speed</string>
    <double>1.0</double>
  </entry>
  <entry>
    <string>Damage</string>
    <integer>30</integer>
  </entry>
  <entry>
    <string>PartKey</string>
    <string>Part2.Projectile</string>
  </entry>
</map>
